{"data":{"success":true,"data":[{"id":389464290,"title":"Getting Over It v1.4","image":"https://cdn2.scratch.mit.edu/get_image/project/389464290_480x360.png","author":"griffpatch","views":"14.8m","loves":"185.5k","favorites":"167.3k"},{"id":389735464,"title":"Getting Over It [Griffpatch Remix]","image":"https://cdn2.scratch.mit.edu/get_image/project/389735464_480x360.png","author":"proprogrammer44","views":"821.1k","loves":"13.8k","favorites":"11.9k"},{"id":396122003,"title":"☁️ Getting Over It Multiplayer Edition 4.2","image":"https://cdn2.scratch.mit.edu/get_image/project/396122003_480x360.png","author":"Ezlambry","views":"364.6k","loves":"8.0k","favorites":"7.2k"},{"id":545941349,"title":"Getting Over It MODES v1.1","image":"https://cdn2.scratch.mit.edu/get_image/project/545941349_480x360.png","author":"GravityV","views":"238.8k","loves":"2.9k","favorites":"3.1k"},{"id":396308487,"title":"Getting Over It HARD MODE","image":"https://cdn2.scratch.mit.edu/get_image/project/396308487_480x360.png","author":"CoolDude76972","views":"111.3k","loves":"625","favorites":"552"},{"id":389774233,"title":"Getting Over It roblox version v2.2","image":"https://cdn2.scratch.mit.edu/get_image/project/389774233_480x360.png","author":"dawoud35","views":"109.1k","loves":"1.7k","favorites":"1.5k"},{"id":392267081,"title":"Getting Over It Hacked","image":"https://cdn2.scratch.mit.edu/get_image/project/392267081_480x360.png","author":"Loupieur","views":"35.8k","loves":"226","favorites":"199"},{"id":385541308,"title":"Getting Over It - Griffpatch","image":"https://cdn2.scratch.mit.edu/get_image/project/385541308_480x360.png","author":"griffpatch_leaks","views":"25.1k","loves":"261","favorites":"243"},{"id":195871723,"title":"getting over it with benett foddy v0.3","image":"https://cdn2.scratch.mit.edu/get_image/project/195871723_480x360.png","author":"23afarnsworth","views":"121.2k","loves":"320","favorites":"269"},{"id":567155857,"title":"Getting Over It ONLINE 3/ゲッティングオーバーイットオンライン 3","image":"https://cdn2.scratch.mit.edu/get_image/project/567155857_480x360.png","author":"pocopocojohn","views":"25.7k","loves":"609","favorites":"569"},{"id":725163900,"title":"Getting Over It v1.4 ⭐BEST MOD PACK⭐","image":"https://cdn2.scratch.mit.edu/get_image/project/725163900_480x360.png","author":"Hananku","views":"33.5k","loves":"386","favorites":"387"},{"id":398785893,"title":"Basically Getting Over it (ft. Etalion)","image":"https://cdn2.scratch.mit.edu/get_image/project/398785893_480x360.png","author":"Meekaryo","views":"19.7k","loves":"419","favorites":"346"},{"id":390281791,"title":"Getting Over It {100's OF LEVELS}","image":"https://cdn2.scratch.mit.edu/get_image/project/390281791_480x360.png","author":"geckos121-TEST","views":"28.6k","loves":"333","favorites":"306"},{"id":683245766,"title":"Getting Over It v1.4","image":"https://cdn2.scratch.mit.edu/get_image/project/683245766_480x360.png","author":"Krinlunch","views":"3.1k","loves":"140","favorites":"125"},{"id":417147569,"title":"[Sideways] Getting Over It V1.4","image":"https://cdn2.scratch.mit.edu/get_image/project/417147569_480x360.png","author":"04tmoody-collab","views":"8.7k","loves":"130","favorites":"112"},{"id":421747841,"title":"Getting Over It A Platformer","image":"https://cdn2.scratch.mit.edu/get_image/project/421747841_480x360.png","author":"Badman1254","views":"8.1k","loves":"120","favorites":"116"},{"id":408503074,"title":"Getting Over It - Multiplayer","image":"https://cdn2.scratch.mit.edu/get_image/project/408503074_480x360.png","author":"cs4079414","views":"4.2k","loves":"87","favorites":"82"},{"id":390366521,"title":"Getting Over It HACKED","image":"https://cdn2.scratch.mit.edu/get_image/project/390366521_480x360.png","author":"yupery","views":"5.1k","loves":"66","favorites":"64"},{"id":393492363,"title":"Mario getting over it","image":"https://cdn2.scratch.mit.edu/get_image/project/393492363_480x360.png","author":"ttps8160549","views":"8.1k","loves":"48","favorites":"37"},{"id":391872023,"title":"Getting Over It v1.4 Moon Gravity","image":"https://cdn2.scratch.mit.edu/get_image/project/391872023_480x360.png","author":"laurensp22","views":"11.2k","loves":"152","favorites":"134"},{"id":548488615,"title":"Getting Over It V1.1","image":"https://cdn2.scratch.mit.edu/get_image/project/548488615_480x360.png","author":"underscore7654","views":"4.1k","loves":"63","favorites":"57"},{"id":389775145,"title":"Getting Over It v1.0 remix","image":"https://cdn2.scratch.mit.edu/get_image/project/389775145_480x360.png","author":"Danneskiten","views":"105.9k","loves":"24","favorites":"17"},{"id":397021828,"title":"Getting Over It But The Lava Rises v2.0","image":"https://cdn2.scratch.mit.edu/get_image/project/397021828_480x360.png","author":"theemeraldsword85","views":"15.3k","loves":"297","favorites":"278"},{"id":548082789,"title":"Getting Over It MODES HACKED","image":"https://cdn2.scratch.mit.edu/get_image/project/548082789_480x360.png","author":"Kaiwentheking","views":"4.1k","loves":"78","favorites":"91"},{"id":390030816,"title":"Getting Over It Hacked!","image":"https://cdn2.scratch.mit.edu/get_image/project/390030816_480x360.png","author":"MichaelHero","views":"3.1k","loves":"49","favorites":"46"},{"id":603616042,"title":"Getting Over It gravity slider","image":"https://cdn2.scratch.mit.edu/get_image/project/603616042_480x360.png","author":"mr_manlyman9","views":"5.4k","loves":"54","favorites":"53"},{"id":424361435,"title":"Getting Over It Speedrun Edition","image":"https://cdn2.scratch.mit.edu/get_image/project/424361435_480x360.png","author":"NoleySpidey","views":"7.5k","loves":"46","favorites":"37"},{"id":426499797,"title":"Getting Over It v1.4 upside-down","image":"https://cdn2.scratch.mit.edu/get_image/project/426499797_480x360.png","author":"Caden00","views":"5.2k","loves":"112","favorites":"99"},{"id":548780229,"title":"Getting Over It Easy Shortgun mode","image":"https://cdn2.scratch.mit.edu/get_image/project/548780229_480x360.png","author":"zombs2002","views":"7.0k","loves":"95","favorites":"111"},{"id":421056559,"title":"Getting Over It Training","image":"https://cdn2.scratch.mit.edu/get_image/project/421056559_480x360.png","author":"Badman1254","views":"2.5k","loves":"43","favorites":"40"},{"id":773603105,"title":"Getting Over It MOD PACK","image":"https://cdn2.scratch.mit.edu/get_image/project/773603105_480x360.png","author":"eeeeeee3e3e3","views":"5.2k","loves":"49","favorites":"46"},{"id":592982090,"title":"Getting Over It HACK","image":"https://cdn2.scratch.mit.edu/get_image/project/592982090_480x360.png","author":"_SCRATCHING_CAT","views":"4.2k","loves":"31","favorites":"24"},{"id":392624758,"title":"Getting Over It [space Edition]","image":"https://cdn2.scratch.mit.edu/get_image/project/392624758_480x360.png","author":"coolkid111_","views":"3.8k","loves":"50","favorites":"45"},{"id":393168382,"title":"Getting Over It Upside-Down","image":"https://cdn2.scratch.mit.edu/get_image/project/393168382_480x360.png","author":"laurensp22","views":"5.0k","loves":"43","favorites":"34"},{"id":391486345,"title":"minecraft Getting Over it","image":"https://cdn2.scratch.mit.edu/get_image/project/391486345_480x360.png","author":"Toy1207chica","views":"3.0k","loves":"33","favorites":"24"},{"id":390217571,"title":"Getting Over It","image":"https://cdn2.scratch.mit.edu/get_image/project/390217571_480x360.png","author":"Pol639","views":"3.1k","loves":"33","favorites":"31"},{"id":429943833,"title":"getting over it [minecraft edition]","image":"https://cdn2.scratch.mit.edu/get_image/project/429943833_480x360.png","author":"mera_naam_shinchan","views":"4.4k","loves":"44","favorites":"37"},{"id":420291623,"title":"Getting Over It: Space Edition re textured","image":"https://cdn2.scratch.mit.edu/get_image/project/420291623_480x360.png","author":"norsecoder452017","views":"6.4k","loves":"71","favorites":"66"},{"id":411441984,"title":"Getting Over It - HARD MODE","image":"https://cdn2.scratch.mit.edu/get_image/project/411441984_480x360.png","author":"NiceGuy5","views":"4.2k","loves":"43","favorites":"33"},{"id":446245522,"title":"Getting Over It MOON GRAVITY","image":"https://cdn2.scratch.mit.edu/get_image/project/446245522_480x360.png","author":"teamturpin","views":"6.2k","loves":"34","favorites":"35"}],"error":""},"timestamp":1736508109658,"expiresIn":86400000}